sswg.py
sswg-4.2.0.dist-info/licenses/LICENSE
sswg-4.2.0.dist-info/METADATA
sswg-4.2.0.dist-info/WHEEL
sswg-4.2.0.dist-info/top_level.txt
sswg-4.2.0.dist-info/RECORD
